add/__init__.py
add/addone.py
sub/__init__.py
sub/subone.py
addorsub-0.0.2.dist-info/LICENSE
addorsub-0.0.2.dist-info/METADATA
addorsub-0.0.2.dist-info/WHEEL
addorsub-0.0.2.dist-info/top_level.txt
addorsub-0.0.2.dist-info/RECORD
