Metadata-Version: 2.1
Name: addorsub
Version: 0.0.2
Summary: Add or Sub one
Home-page: https://blog.xiaoqying.com
Author: tongye
Author-email: 791161009@qq.com
License: UNKNOWN
Platform: UNKNOWN
Classifier: Programming Language :: Python :: 3
Classifier: License :: OSI Approved :: MIT License
Classifier: Operating System :: OS Independent
Requires-Python: >=3.6
License-File: LICENSE
